[
    {
        "question": {
            "type": "image",
            "content": "images/images69/1.png"
        },
        "answer": {
            "type": "image",
            "content": "images/images69/1-.png"
        }
    },
    {
        "question": {
            "type": "image",
            "content": "images/images69/2.png"
        },
        "answer": {
            "type": "image",
            "content": "images/images69/2-.png"
        }
    },
    {
        "question": {
            "type": "image",
            "content": "images/images69/3.png"
        },
        "answer": {
            "type": "image",
            "content": "images/images69/3-.png"
        }
    },
    {
        "question": {
            "type": "image",
            "content": "images/images69/4.png"
        },
        "answer": {
            "type": "image",
            "content": "images/images69/4-.png"
        }
    },
    {
        "question": {
            "type": "image",
            "content": "images/images69/5.png"
        },
        "answer": {
            "type": "image",
            "content": "images/images69/5-.png"
        }
    },
    {
        "question": {
            "type": "image",
            "content": "images/images69/6.png"
        },
        "answer": {
            "type": "image",
            "content": "images/images69/6-.png"
        }
    },
    {
        "question": {
            "type": "image",
            "content": "images/images69/7.png"
        },
        "answer": {
            "type": "image",
            "content": "images/images69/7-.png"
        }
    }
]
